[{"title":"デート～恋とはどんなものかしら～ 第10話 720p HDTV x264 AAC-DoA","value":["loadfile","/run/media/zen/HGST/torrent/temp/Date - Koi to wa Donna Mono Kashira (2015)/Date ep10 finale (848x480 x264).mkv"],"hint":"MKV | 12/27 18:24"},{"title":"SDMT-593","value":["loadfile","/mnt/zen/complete/SDMT-593.mp4"],"hint":"MP4 | 12/25 20:08"},{"title":"MIDA-031","value":["loadfile","/mnt/zen/complete/MIDA-031.mp4"],"hint":"MP4 | 12/25 20:08"},{"title":"SDJS-065","value":["loadfile","/mnt/zen/face/SDJS-065.mp4"],"hint":"MP4 | 12/24 00:37"},{"title":"PGD-491","value":["loadfile","/mnt/zen/face/PGD-491.mkv"],"hint":"MKV | 12/23 23:20"},{"title":"Naked school watch online","value":["loadfile","/mnt/zen/download/Naked school watch online.mp4"],"hint":"MP4 | 12/23 23:13"},{"title":"MKMP-184","value":["loadfile","/mnt/zen/face/MKMP-184.mp4"],"hint":"MP4 | 12/23 23:08"},{"title":"MIDE-790","value":["loadfile","/mnt/zen/face/MIDE-790.mp4"],"hint":"MP4 | 12/23 22:47"},{"title":"HND-532","value":["loadfile","/mnt/zen/face/HND-532.mp4"],"hint":"MP4 | 12/23 22:39"},{"title":"MDB-767","value":["loadfile","/mnt/zen/complete/MDB-767.mp4"],"hint":"MP4 | 12/23 21:47"}]